setup.py
enter_key/__init__.py
enter_key/admin.py
enter_key/apps.py
enter_key/models.py
enter_key/tests.py
enter_key/urls.py
enter_key/views.py
enter_key/migrations/__init__.py
enterkey.egg-info/PKG-INFO
enterkey.egg-info/SOURCES.txt
enterkey.egg-info/dependency_links.txt
enterkey.egg-info/requires.txt
enterkey.egg-info/top_level.txt