Metadata-Version: 2.1
Name: enterkey
Version: 0.1
Summary: only enter key
Home-page: UNKNOWN
Author: Prince Kathuria
Author-email: pk.kathuria9213@gmail.com
License: UNKNOWN
Platform: UNKNOWN
